mitmproxy_rs-0.12.5.dist-info/METADATA
mitmproxy_rs-0.12.5.dist-info/WHEEL
mitmproxy_rs-0.12.5.dist-info/entry_points.txt
mitmproxy_rs/__init__.py
mitmproxy_rs/__init__.pyi
mitmproxy_rs/_pyinstaller/__init__.py
mitmproxy_rs/_pyinstaller/hook-mitmproxy_linux.py
mitmproxy_rs/_pyinstaller/hook-mitmproxy_macos.py
mitmproxy_rs/_pyinstaller/hook-mitmproxy_rs.py
mitmproxy_rs/_pyinstaller/hook-mitmproxy_windows.py
mitmproxy_rs/certs.pyi
mitmproxy_rs/contentviews.pyi
mitmproxy_rs/dns.pyi
mitmproxy_rs/local.pyi
mitmproxy_rs/mitmproxy_rs.abi3.so
mitmproxy_rs/process_info.pyi
mitmproxy_rs/py.typed
mitmproxy_rs/syntax_highlight.pyi
mitmproxy_rs/tun.pyi
mitmproxy_rs/udp.pyi
mitmproxy_rs/wireguard.pyi
mitmproxy_rs-0.12.5.dist-info/RECORD
