Metadata-Version: 2.4
Name: mitmproxy_rs
Version: 0.12.5
Classifier: Programming Language :: Rust
Classifier: Programming Language :: Python :: Implementation :: CPython
Classifier: Programming Language :: Python :: Implementation :: PyPy
Classifier: Programming Language :: Python :: 3 :: Only
Classifier: Programming Language :: Python :: 3.12
Classifier: Programming Language :: Python :: 3.13
Classifier: Development Status :: 5 - Production/Stable
Requires-Dist: mitmproxy-windows==0.12.5 ; os_name == 'nt'
Requires-Dist: mitmproxy-linux==0.12.5 ; sys_platform == 'linux'
Requires-Dist: mitmproxy-macos==0.12.5 ; sys_platform == 'darwin'
Author: Fabio Valentini <decathorpe@gmail.com>, Maximilian Hils <cargo@maximilianhils.com>
Author-email: Fabio Valentini <decathorpe@gmail.com>, Maximilian Hils <cargo@maximilianhils.com>
License: MIT
Requires-Python: >=3.12
Project-URL: Source Code, https://github.com/mitmproxy/mitmproxy-rs
